osg/__init__.py
osg/flamegraph.py
osg/pandas.py
osg/plot.py
osgpy-0.1.5.data/data/requirements.txt
osgpy-0.1.5.dist-info/METADATA
osgpy-0.1.5.dist-info/WHEEL
osgpy-0.1.5.dist-info/top_level.txt
osgpy-0.1.5.dist-info/RECORD
