Metadata-Version: 2.1
Name: osgpy
Version: 0.1.5
Summary: Python utilities of the Operating System Group
Home-page: http://github.com/tuhhosg/osgpy
Author: Christian Dietrich
Author-email: christian.dietrich@tuhh.de
License: MIT
Classifier: Development Status :: 3 - Alpha
Classifier: Environment :: Console
Classifier: Intended Audience :: Science/Research
Classifier: Operating System :: OS Independent
Classifier: Programming Language :: Python :: 3.9
Classifier: Programming Language :: Python :: 3.10
Requires-Python: >=3.9
Requires-Dist: versuchung (>=1.4.1)
Requires-Dist: pandas (>=1.5.1)
Requires-Dist: plotnine (>=0.10.1)
Requires-Dist: plydata (>=0.4.3)
Requires-Dist: scikit-misc (>=0.2.0)
